dwt_audio_stego/__init__.py
dwt_audio_stego/__main__.py
dwt_audio_stego/main.py
dwt_audio_stego-0.1.5.dist-info/METADATA
dwt_audio_stego-0.1.5.dist-info/WHEEL
dwt_audio_stego-0.1.5.dist-info/entry_points.txt
dwt_audio_stego-0.1.5.dist-info/top_level.txt
dwt_audio_stego-0.1.5.dist-info/RECORD
